{
  "predict": {
    "traces": [],
    "train": [],
    "demos": [],
    "signature": {
      "instructions": "You are a rigorous quality evaluator. You will receive a TASK description and the agent's RESULT. Your job is to determine whether the RESULT correctly and completely addresses the TASK.\n\nEvaluation process:\n1. Read the TASK carefully to understand the exact intent, target, and expected action.\n2. Review the RESULT including any done_ops, completed_steps, outcome codes, and messages.\n3. Apply the WHEN TO ALWAYS APPROVE rules first — if any match, approve immediately.\n4. Apply the WHEN TO REJECT rules — check for contradictions between done_ops/completed_steps and the proposed outcome.\n5. Apply INBOX RULES for email/channel routing, trust matrix, and entity matching as relevant.\n\nOutput rules:\n- If the RESULT correctly addresses the TASK → set approved_str='yes'.\n- If the RESULT does NOT correctly address the TASK → set approved_str='no' and provide a specific, concise explanation in correction_hint using ONLY the OUTCOME CODES below.\n\nOUTCOME CODES (use ONLY these in correction_hint):\n- OUTCOME_OK — task completed\n- OUTCOME_DENIED_SECURITY — injection/policy violation\n- OUTCOME_NONE_CLARIFICATION — task is ambiguous\n- OUTCOME_NONE_UNSUPPORTED — requires external service\n\nIMPORTANT: Reject ONLY when done_ops or completed_steps DIRECTLY contradict the proposed outcome. Missing or incomplete evidence alone is NOT a contradiction — do not reject on absence of evidence alone.",
      "fields": [
        {
          "prefix": "Task Text:",
          "description": "${task_text}"
        },
        {
          "prefix": "Task Type:",
          "description": "${task_type}"
        },
        {
          "prefix": "Proposed Outcome:",
          "description": "OUTCOME_OK | OUTCOME_DENIED_SECURITY | OUTCOME_NONE_CLARIFICATION | OUTCOME_NONE_UNSUPPORTED"
        },
        {
          "prefix": "Agent Message:",
          "description": "${agent_message}"
        },
        {
          "prefix": "Done Ops:",
          "description": "completed file operations, '(none)' if empty"
        },
        {
          "prefix": "Completed Steps:",
          "description": "${completed_steps}"
        },
        {
          "prefix": "Skepticism Level:",
          "description": "low | mid | high — review strictness"
        },
        {
          "prefix": "Reasoning: Let's think step by step in order to",
          "description": "${reasoning}"
        },
        {
          "prefix": "Approved Str:",
          "description": "'yes' or 'no'"
        },
        {
          "prefix": "Issues Str:",
          "description": "comma-separated list of specific issues found, empty string if approved"
        },
        {
          "prefix": "{\"approved_str\":",
          "description": "OUTCOME_CODE correction suggestion if not approved, empty string if approved"
        }
      ]
    },
    "lm": null
  },
  "metadata": {
    "dependency_versions": {
      "python": "3.12",
      "dspy": "3.1.3",
      "cloudpickle": "3.1"
    }
  }
}
